{
    "evaluation": {
        "PathCost": 0.0
    },
    "startGoal": {
        "start": [
            0,
            0
        ],
        "goal": [
            5,
            5
        ]
    },
    "pathInfo": {
        "success": 0,
        "path": [],
        "info": [
            "Goal has obstacle"
        ]
    },
    "envInfo": {
        "grid": [
            [
                1.0,
                1.0,
                1.0,
                1.0,
                1.0,
                1.0,
                0.0,
                0.0,
                0.0,
                0.0
            ],
            [
                1.0,
                1.0,
                1.0,
                1.0,
                1.0,
                1.0,
                0.0,
                0.0,
                0.0,
                0.0
            ],
            [
                1.0,
                1.0,
                1.0,
                1.0,
                1.0,
                1.0,
                0.0,
                0.0,
                0.0,
                0.0
            ],
            [
                1.0,
                1.0,
                1.0,
                1.0,
                1.0,
                1.0,
                0.0,
                0.0,
                0.0,
                0.0
            ],
            [
                1.0,
                1.0,
                1.0,
                1.0,
                1.0,
                1.0,
                0.0,
                0.0,
                0.0,
                0.0
            ],
            [
                1.0,
                1.0,
                1.0,
                1.0,
                1.0,
                1.0,
                0.0,
                0.0,
                0.0,
                0.0
            ],
            [
                0.0,
                0.0,
                0.0,
                0.0,
                0.0,
                0.0,
                0.0,
                0.0,
                0.0,
                0.0
            ],
            [
                0.0,
                0.0,
                0.0,
                0.0,
                0.0,
                0.0,
                0.0,
                1.0,
                1.0,
                1.0
            ],
            [
                0.0,
                0.0,
                0.0,
                0.0,
                0.0,
                0.0,
                0.0,
                1.0,
                1.0,
                1.0
            ],
            [
                0.0,
                0.0,
                0.0,
                0.0,
                0.0,
                0.0,
                0.0,
                1.0,
                1.0,
                1.0
            ]
        ],
        "cellSize": 0.5,
        "envName": "Env2",
        "envDes": "Maze type environment"
    }
}